hypothesis_awkward/__about__.py
hypothesis_awkward/__init__.py
hypothesis_awkward/py.typed
hypothesis_awkward/strategies/__init__.py
hypothesis_awkward/strategies/builtins_/__init__.py
hypothesis_awkward/strategies/builtins_/dtype.py
hypothesis_awkward/strategies/builtins_/list_.py
hypothesis_awkward/strategies/misc/__init__.py
hypothesis_awkward/strategies/misc/idiom.py
hypothesis_awkward/strategies/misc/range.py
hypothesis_awkward/strategies/numpy/__init__.py
hypothesis_awkward/strategies/numpy/dtype.py
hypothesis_awkward/strategies/numpy/numpy.py
hypothesis_awkward/strategies/pandas/__init__.py
hypothesis_awkward/strategies/pandas/dict_.py
hypothesis_awkward/util/__init__.py
hypothesis_awkward/util/awkward.py
hypothesis_awkward/util/dtype.py
hypothesis_awkward/util/numpy.py
hypothesis_awkward/util/safe.py
hypothesis_awkward-0.0.5.dist-info/METADATA
hypothesis_awkward-0.0.5.dist-info/WHEEL
hypothesis_awkward-0.0.5.dist-info/licenses/LICENSE
hypothesis_awkward-0.0.5.dist-info/RECORD
